{
  "edition_id": "2026-04-18-forest-listening-table-v2",
  "date": "2026-04-18",
  "status": "review",
  "slug": "forest-listening-table-v2",
  "title": "Forest Listening Table R2",
  "scene_family": "forest-listening-table",
  "brief_id": "brief-2026-04-17-2",
  "plate_id": "plate-2026-04-17-2",
  "artifact_map_id": "map-2026-04-17-2",
  "source_binding_set_id": "bindings-2026-04-17-2",
  "ambiance_recipe_id": "ambiance-2026-04-17-2",
  "review_state_id": "review-2026-04-17-2",
  "publish_state": {
    "is_live": false,
    "published_at": null,
    "archive_path": "/archive/forest-listening-table-v2"
  },
  "plate_asset_path": "/editions/2026-04-18-forest-listening-table-v2/assets/plate.jpg"
}
